BuildYourOwnEmbedding/__init__.py
BuildYourOwnEmbedding/functional.py
BuildYourOwnEmbedding/generate_docs.py
BuildYourOwnEmbedding/parameters.py
BuildYourOwnEmbedding/responses.py
BuildYourOwnEmbedding-1.1.dist-info/LICENSE
BuildYourOwnEmbedding-1.1.dist-info/METADATA
BuildYourOwnEmbedding-1.1.dist-info/WHEEL
BuildYourOwnEmbedding-1.1.dist-info/top_level.txt
BuildYourOwnEmbedding-1.1.dist-info/RECORD
